{
  "_class": "group",
  "booleanOperation": -1,
  "clippingMaskMode": 0,
  "do_objectID": "AB633E09-42F6-4FAF-9530-D0D8F1BB75AF",
  "exportOptions": {
    "_class": "exportOptions",
    "do_objectID": "A0227155-77FA-4DC6-9425-E14EA450F78B",
    "exportFormats": [
    ],
    "includedLayerIds": [
    ],
    "layerOptions": 0,
    "shouldTrim": false
  },
  "frame": {
    "_class": "rect",
    "constrainProportions": false,
    "do_objectID": "623ADD3D-A798-4107-BBAC-C83F38AF392E",
    "height": 13,
    "width": 72,
    "x": 8,
    "y": 3.851620197887996
  },
  "groupLayout": {
    "_class": "MSImmutableFreeformGroupLayout",
    "do_objectID": "F0579123-F102-4CAC-B33A-A687E607E0FB"
  },
  "hasClickThrough": false,
  "hasClippingMask": false,
  "isFixedToViewport": false,
  "isFlippedHorizontal": false,
  "isFlippedVertical": false,
  "isLocked": false,
  "isVisible": true,
  "layerListExpandedType": 0,
  "layers": [
    {
      "class": "group",
      "id": "F6E29BBA-2538-4F45-89E7-9561ED17B0A5"
    },
    {
      "class": "text",
      "id": "FF8C47B5-0577-4C0D-A599-2F07ADE2F458"
    },
    {
      "class": "shapeGroup",
      "id": "213EB044-3099-4F45-8FAF-2B4F99245BFD"
    }
  ],
  "name": "Group",
  "nameIsFixed": false,
  "resizingConstraint": 59,
  "resizingType": 0,
  "rotation": 0,
  "shouldBreakMaskChain": false,
  "style": {
    "_class": "style",
    "do_objectID": "ED4F1C4A-063D-49AE-8A35-F28DB04125F3",
    "endMarkerType": 0,
    "miterLimit": 10,
    "startMarkerType": 0,
    "windingRule": 1
  }
}