{
  "_class": "shapeGroup",
  "booleanOperation": 0,
  "clippingMaskMode": 0,
  "do_objectID": "CA0C628D-9175-4864-AA9F-ED0272FD8635",
  "exportOptions": {
    "_class": "exportOptions",
    "do_objectID": "D8DDD39E-527B-4184-9A72-48AA250BACD1",
    "exportFormats": [
    ],
    "includedLayerIds": [
    ],
    "layerOptions": 0,
    "shouldTrim": false
  },
  "frame": {
    "_class": "rect",
    "constrainProportions": true,
    "do_objectID": "2159AA1E-3541-4438-B77A-7878DDB6B1B9",
    "height": 16,
    "width": 16,
    "x": 0,
    "y": 4
  },
  "groupLayout": {
    "_class": "MSImmutableFreeformGroupLayout",
    "do_objectID": "83193A2C-6267-4B13-ADC4-702CE65E26E2"
  },
  "hasClickThrough": false,
  "hasClippingMask": false,
  "isFixedToViewport": false,
  "isFlippedHorizontal": false,
  "isFlippedVertical": false,
  "isLocked": false,
  "isVisible": true,
  "layerListExpandedType": 1,
  "layers": [
    {
      "class": "oval",
      "id": "BF2326D1-A3BC-4256-BCA7-443099219AA6"
    },
    {
      "class": "shapePath",
      "id": "C6F320A8-0641-4002-B018-097F94E00624"
    },
    {
      "class": "shapePath",
      "id": "5A4B87E5-B8CD-410D-84E5-9861BF1822F9"
    }
  ],
  "name": "Combined Shape Copy",
  "nameIsFixed": false,
  "resizingConstraint": 63,
  "resizingType": 0,
  "rotation": 0,
  "shouldBreakMaskChain": false,
  "style": {
    "_class": "style",
    "borders": [
      {
        "_class": "border",
        "color": {
          "_class": "color",
          "alpha": 1,
          "blue": 0.592,
          "green": 0.592,
          "red": 0.592
        },
        "fillType": 0,
        "isEnabled": false,
        "position": 0,
        "thickness": 2
      }
    ],
    "do_objectID": "194B588E-8CAB-467F-9EAF-51F00C16D796",
    "endMarkerType": 0,
    "fills": [
      {
        "_class": "fill",
        "color": {
          "_class": "color",
          "alpha": 1,
          "blue": 0,
          "green": 0,
          "red": 0
        },
        "fillType": 1,
        "gradient": {
          "_class": "gradient",
          "elipseLength": 0,
          "from": "{0.5, 0}",
          "gradientType": 0,
          "stops": [
            {
              "_class": "gradientStop",
              "color": {
                "_class": "color",
                "alpha": 1,
                "blue": 0.5647058824,
                "green": 0.3254901961,
                "red": 0.05098039216
              },
              "position": 0
            },
            {
              "_class": "gradientStop",
              "color": {
                "_class": "color",
                "alpha": 1,
                "blue": 0.4243376358695652,
                "green": 0.23209714554396,
                "red": 0.01137658257752438
              },
              "position": 1
            }
          ],
          "to": "{0.5, 1}"
        },
        "isEnabled": true,
        "noiseIndex": 0,
        "noiseIntensity": 0,
        "patternFillType": 1,
        "patternTileScale": 1
      }
    ],
    "miterLimit": 10,
    "startMarkerType": 0,
    "windingRule": 1
  },
  "windingRule": 1
}