{
  "_class": "shapePath",
  "booleanOperation": -1,
  "clippingMaskMode": 0,
  "do_objectID": "1A058850-FAE9-461F-9ABC-55004A63B4D8",
  "edited": true,
  "exportOptions": {
    "_class": "exportOptions",
    "do_objectID": "985DE2BC-70BE-4CAB-B955-9E92D6C81F7F",
    "exportFormats": [
    ],
    "includedLayerIds": [
    ],
    "layerOptions": 0,
    "shouldTrim": false
  },
  "frame": {
    "_class": "rect",
    "constrainProportions": false,
    "do_objectID": "448CCA81-EEAF-4BF6-B3F5-3A3AFBC8F235",
    "height": 1,
    "width": 375,
    "x": 1,
    "y": 68
  },
  "hasClippingMask": false,
  "isClosed": false,
  "isFixedToViewport": false,
  "isFlippedHorizontal": false,
  "isFlippedVertical": false,
  "isLocked": false,
  "isVisible": true,
  "layerListExpandedType": 0,
  "name": "Line Copy 7",
  "nameIsFixed": false,
  "pointRadiusBehaviour": 1,
  "points": [
    {
      "_class": "curvePoint",
      "cornerRadius": 0,
      "curveFrom": "{0, 0.5}",
      "curveMode": 1,
      "curveTo": "{0, 0.5}",
      "hasCurveFrom": false,
      "hasCurveTo": false,
      "point": "{0, 0.5}"
    },
    {
      "_class": "curvePoint",
      "cornerRadius": 0,
      "curveFrom": "{0, 0.5}",
      "curveMode": 1,
      "curveTo": "{0, 0.5}",
      "hasCurveFrom": false,
      "hasCurveTo": false,
      "point": "{1.0000000000000002, 0.5}"
    }
  ],
  "resizingConstraint": 63,
  "resizingType": 0,
  "rotation": 0,
  "shouldBreakMaskChain": false,
  "style": {
    "_class": "style",
    "borderOptions": {
      "_class": "borderOptions",
      "dashPattern": [
      ],
      "do_objectID": "92B35F07-3FE2-4216-9785-D85679D84568",
      "isEnabled": false,
      "lineCapStyle": 2,
      "lineJoinStyle": 0
    },
    "borders": [
      {
        "_class": "border",
        "color": {
          "_class": "color",
          "alpha": 1,
          "blue": 0.8588235294117647,
          "green": 0.8313725490196078,
          "red": 0.8117647058823529
        },
        "fillType": 0,
        "isEnabled": true,
        "position": 0,
        "thickness": 1
      }
    ],
    "do_objectID": "6CD87B7C-CDCE-4EBD-BE4A-FA36409D8B9F",
    "endMarkerType": 0,
    "fills": [
      {
        "_class": "fill",
        "color": {
          "_class": "color",
          "alpha": 1,
          "blue": 0.847,
          "green": 0.847,
          "red": 0.847
        },
        "fillType": 0,
        "isEnabled": false,
        "noiseIndex": 0,
        "noiseIntensity": 0,
        "patternFillType": 1,
        "patternTileScale": 1
      }
    ],
    "miterLimit": 10,
    "startMarkerType": 0,
    "windingRule": 1
  }
}