{
  "_class": "group",
  "booleanOperation": -1,
  "clippingMaskMode": 0,
  "do_objectID": "E909A6FF-FB40-4CC3-97E5-0A195A6E011E",
  "exportOptions": {
    "_class": "exportOptions",
    "do_objectID": "320E755C-20AC-4485-BEFD-4662F21F2287",
    "exportFormats": [
    ],
    "includedLayerIds": [
    ],
    "layerOptions": 0,
    "shouldTrim": false
  },
  "frame": {
    "_class": "rect",
    "constrainProportions": true,
    "do_objectID": "C5EB6C71-5358-48D2-A090-A8A43AE87DC5",
    "height": 11,
    "width": 13.75,
    "x": 3952.444444444444,
    "y": 346.3333333333334
  },
  "groupLayout": {
    "_class": "MSImmutableFreeformGroupLayout",
    "do_objectID": "54C9A8C1-B8CE-454D-9B64-4E415DDF0899"
  },
  "hasClickThrough": false,
  "hasClippingMask": false,
  "isFixedToViewport": false,
  "isFlippedHorizontal": false,
  "isFlippedVertical": false,
  "isLocked": false,
  "isVisible": true,
  "layerListExpandedType": 2,
  "layers": [
    {
      "class": "shapePath",
      "id": "74BF9BDD-9179-4EB4-A321-0E24F524FDD4"
    }
  ],
  "name": "noun-arrow-77061 copy 4",
  "nameIsFixed": false,
  "resizingConstraint": 63,
  "resizingType": 0,
  "rotation": 0,
  "shouldBreakMaskChain": false,
  "style": {
    "_class": "style",
    "do_objectID": "9730CF99-F067-4729-96E3-616B49DCC79A",
    "endMarkerType": 0,
    "miterLimit": 10,
    "startMarkerType": 0,
    "windingRule": 1
  }
}