{
  "_class": "group",
  "booleanOperation": -1,
  "clippingMaskMode": 0,
  "do_objectID": "134E47BB-0F7A-4BF9-922E-9F7249CC602F",
  "exportOptions": {
    "_class": "exportOptions",
    "do_objectID": "E27A3C4B-16C8-44F2-A434-94E13D9EF5F2",
    "exportFormats": [
    ],
    "includedLayerIds": [
    ],
    "layerOptions": 0,
    "shouldTrim": false
  },
  "frame": {
    "_class": "rect",
    "constrainProportions": true,
    "do_objectID": "536C6515-57F4-4EB0-82B4-AC1A0DD9A924",
    "height": 30,
    "width": 33,
    "x": 0,
    "y": 5
  },
  "groupLayout": {
    "_class": "MSImmutableFreeformGroupLayout",
    "do_objectID": "19C8C6DF-07AD-44D7-B3D1-B29EB8485CFF"
  },
  "hasClickThrough": false,
  "hasClippingMask": false,
  "isFixedToViewport": false,
  "isFlippedHorizontal": false,
  "isFlippedVertical": false,
  "isLocked": false,
  "isVisible": true,
  "layerListExpandedType": 2,
  "layers": [
    {
      "class": "group",
      "id": "0A457446-D355-453D-AA9B-BE7CF11A2E51"
    }
  ],
  "name": "noun_profile_2200074 copy 6",
  "nameIsFixed": false,
  "resizingConstraint": 63,
  "resizingType": 0,
  "rotation": 0,
  "shouldBreakMaskChain": false,
  "style": {
    "_class": "style",
    "do_objectID": "E9D53F2C-F39A-47D8-9D7B-381217F15CBF",
    "endMarkerType": 0,
    "miterLimit": 10,
    "startMarkerType": 0,
    "windingRule": 1
  }
}