{
  "_class": "shapeGroup",
  "booleanOperation": 0,
  "clippingMaskMode": 0,
  "do_objectID": "4BAFB994-1EED-4A9B-9F3B-26C40E56B048",
  "exportOptions": {
    "_class": "exportOptions",
    "do_objectID": "A9D7F1AB-8319-4DB9-8647-00BA14461E88",
    "exportFormats": [
    ],
    "includedLayerIds": [
    ],
    "layerOptions": 0,
    "shouldTrim": false
  },
  "frame": {
    "_class": "rect",
    "constrainProportions": false,
    "do_objectID": "DE6AA484-4776-4637-8E37-B9A6D3515A87",
    "height": 4.878617543688772,
    "width": 4.878617543688762,
    "x": 18.6274488031753,
    "y": 0
  },
  "groupLayout": {
    "_class": "MSImmutableFreeformGroupLayout",
    "do_objectID": "3A3EE20A-CFBC-4530-A345-159E94E33322"
  },
  "hasClickThrough": false,
  "hasClippingMask": false,
  "isFixedToViewport": false,
  "isFlippedHorizontal": false,
  "isFlippedVertical": false,
  "isLocked": false,
  "isVisible": true,
  "layerListExpandedType": 0,
  "layers": [
    {
      "class": "shapePath",
      "id": "8BF8A404-5F15-4484-8E39-AB5AAC6B1428"
    },
    {
      "class": "shapePath",
      "id": "6706D33F-4F9E-4338-BF01-7C5210A0F40E"
    }
  ],
  "name": "Shape",
  "nameIsFixed": false,
  "originalObjectID": "8F663339-BF69-46A5-A284-36A64BF7AEBF",
  "resizingConstraint": 59,
  "resizingType": 0,
  "rotation": 0,
  "shouldBreakMaskChain": false,
  "style": {
    "_class": "style",
    "blur": {
      "_class": "blur",
      "center": "{0.5, 0.5}",
      "do_objectID": "59DD75AC-D506-4F4B-989C-0E020CBABA1C",
      "isEnabled": false,
      "motionAngle": 0,
      "radius": 4.3,
      "saturation": 1,
      "type": 0
    },
    "do_objectID": "E076F6CF-BFA3-4155-8269-F2A9458C9A7C",
    "endMarkerType": 0,
    "fills": [
      {
        "_class": "fill",
        "color": {
          "_class": "color",
          "alpha": 1,
          "blue": 0,
          "green": 0,
          "red": 0
        },
        "fillType": 0,
        "isEnabled": true,
        "noiseIndex": 0,
        "noiseIntensity": 0,
        "patternFillType": 0,
        "patternTileScale": 1
      }
    ],
    "miterLimit": 10,
    "startMarkerType": 0,
    "windingRule": 0
  },
  "windingRule": 0
}