{
  "_class": "group",
  "booleanOperation": -1,
  "clippingMaskMode": 0,
  "do_objectID": "F9119B0D-9B37-407B-A8E5-733E0E4FF2AE",
  "exportOptions": {
    "_class": "exportOptions",
    "do_objectID": "18EB6326-84F4-45A1-8471-55BF459F6255",
    "exportFormats": [
    ],
    "includedLayerIds": [
    ],
    "layerOptions": 0,
    "shouldTrim": false
  },
  "frame": {
    "_class": "rect",
    "constrainProportions": false,
    "do_objectID": "36C57564-EA9C-4A0B-98EA-B287824455FC",
    "height": 40,
    "width": 40,
    "x": 0,
    "y": 0
  },
  "groupLayout": {
    "_class": "MSImmutableFreeformGroupLayout",
    "do_objectID": "4ACD8E62-955D-42CF-8B4B-71A5D46B2D86"
  },
  "hasClickThrough": false,
  "hasClippingMask": false,
  "isFixedToViewport": false,
  "isFlippedHorizontal": false,
  "isFlippedVertical": false,
  "isLocked": false,
  "isVisible": true,
  "layerListExpandedType": 0,
  "layers": [
    {
      "class": "oval",
      "id": "E8066C5E-62ED-4445-8594-AAFF59214DE8"
    },
    {
      "class": "text",
      "id": "339165C5-9E7E-422E-BFF1-12AD7FF4D1F3"
    }
  ],
  "name": "Group 7",
  "nameIsFixed": false,
  "resizingConstraint": 63,
  "resizingType": 0,
  "rotation": 0,
  "shouldBreakMaskChain": false,
  "style": {
    "_class": "style",
    "do_objectID": "F77AD0FB-B204-45B4-9B88-7AA446039195",
    "endMarkerType": 0,
    "miterLimit": 10,
    "startMarkerType": 0,
    "windingRule": 1
  }
}