{
  "_class": "group",
  "booleanOperation": -1,
  "clippingMaskMode": 0,
  "do_objectID": "C0CE7227-1A05-4E77-921C-E0834A1CC279",
  "exportOptions": {
    "_class": "exportOptions",
    "do_objectID": "88BA3695-BF98-470A-9D91-AC0F2DCD3605",
    "exportFormats": [
    ],
    "includedLayerIds": [
    ],
    "layerOptions": 0,
    "shouldTrim": false
  },
  "frame": {
    "_class": "rect",
    "constrainProportions": false,
    "do_objectID": "223DB549-9ED0-4DFD-AE4A-4D669E93D0A0",
    "height": 56,
    "width": 376,
    "x": 0,
    "y": 1072
  },
  "groupLayout": {
    "_class": "MSImmutableFreeformGroupLayout",
    "do_objectID": "6F20769D-C6B7-4A1C-B7D3-EA601DF37125"
  },
  "hasClickThrough": false,
  "hasClippingMask": false,
  "isFixedToViewport": false,
  "isFlippedHorizontal": false,
  "isFlippedVertical": false,
  "isLocked": false,
  "isVisible": true,
  "layerListExpandedType": 0,
  "layers": [
    {
      "class": "rectangle",
      "id": "190A8FA3-A8FF-415C-A0E4-DD85121A2F5B"
    },
    {
      "class": "rectangle",
      "id": "6DDE70CB-36DE-4DA6-8F95-AE1A11DB9410"
    },
    {
      "class": "text",
      "id": "086F6416-F9F0-48EA-8F07-CD0B004C53E1"
    }
  ],
  "name": "Group 9 Copy",
  "nameIsFixed": false,
  "resizingConstraint": 63,
  "resizingType": 0,
  "rotation": 0,
  "shouldBreakMaskChain": false,
  "style": {
    "_class": "style",
    "do_objectID": "A31B6E2E-98BF-4A93-AD34-05C9030AC5B3",
    "endMarkerType": 0,
    "miterLimit": 10,
    "startMarkerType": 0,
    "windingRule": 1
  }
}