{
  "_class": "text",
  "attributedString": {
    "_class": "attributedString",
    "attributes": [
      {
        "_class": "stringAttribute",
        "attributes": {
          "MSAttributedStringColorAttribute": {
            "_class": "color",
            "alpha": 1,
            "blue": 0.2392156863,
            "green": 0.1333333333,
            "red": 0.01176470588
          },
          "MSAttributedStringFontAttribute": {
            "_class": "fontDescriptor",
            "attributes": {
              "name": "HelveticaNeue",
              "size": 14
            }
          },
          "kerning": 0,
          "paragraphStyle": {
            "_class": "paragraphStyle",
            "alignment": 1,
            "allowsDefaultTighteningForTruncation": 0,
            "maximumLineHeight": 20,
            "minimumLineHeight": 20
          }
        },
        "length": 3,
        "location": 0
      },
      {
        "_class": "stringAttribute",
        "attributes": {
          "MSAttributedStringColorAttribute": {
            "_class": "color",
            "alpha": 1,
            "blue": 0.2392156863,
            "green": 0.1333333333,
            "red": 0.01176470588
          },
          "MSAttributedStringFontAttribute": {
            "_class": "fontDescriptor",
            "attributes": {
              "name": "HelveticaNeue-Medium",
              "size": 16
            }
          },
          "kerning": 0,
          "paragraphStyle": {
            "_class": "paragraphStyle",
            "alignment": 1,
            "allowsDefaultTighteningForTruncation": 0,
            "maximumLineHeight": 20,
            "minimumLineHeight": 20
          }
        },
        "length": 1,
        "location": 3
      },
      {
        "_class": "stringAttribute",
        "attributes": {
          "MSAttributedStringColorAttribute": {
            "_class": "color",
            "alpha": 1,
            "blue": 0.2392156863,
            "green": 0.1333333333,
            "red": 0.01176470588
          },
          "MSAttributedStringFontAttribute": {
            "_class": "fontDescriptor",
            "attributes": {
              "name": "HelveticaNeue-Bold",
              "size": 16
            }
          },
          "kerning": 0,
          "paragraphStyle": {
            "_class": "paragraphStyle",
            "alignment": 1,
            "allowsDefaultTighteningForTruncation": 0,
            "maximumLineHeight": 20,
            "minimumLineHeight": 20
          }
        },
        "length": 10,
        "location": 4
      }
    ],
    "string": "EUR 156,635.28"
  },
  "automaticallyDrawOnUnderlyingPath": false,
  "booleanOperation": 0,
  "clippingMaskMode": 0,
  "do_objectID": "036C44E5-71E5-4B01-89D7-DD2DD66049B4",
  "dontSynchroniseWithSymbol": true,
  "exportOptions": {
    "_class": "exportOptions",
    "do_objectID": "D8651D74-CD4A-421E-9094-B8DD7C2FFDD6",
    "exportFormats": [
    ],
    "includedLayerIds": [
    ],
    "layerOptions": 0,
    "shouldTrim": false
  },
  "frame": {
    "_class": "rect",
    "constrainProportions": false,
    "do_objectID": "8D4F0530-E99A-4832-9DE6-BE9B4E2332FD",
    "height": 20,
    "width": 113,
    "x": 214,
    "y": 16
  },
  "glyphBounds": "{{1, 5}, {112, 15}}",
  "hasClippingMask": false,
  "isFixedToViewport": false,
  "isFlippedHorizontal": false,
  "isFlippedVertical": false,
  "isLocked": false,
  "isVisible": true,
  "layerListExpandedType": 0,
  "lineSpacingBehaviour": 2,
  "name": "EUR 156,635.28",
  "nameIsFixed": false,
  "originalObjectID": "78634B75-EF63-4364-8903-DAABA85CCBED",
  "resizingConstraint": 47,
  "resizingType": 0,
  "rotation": 0,
  "shouldBreakMaskChain": false,
  "style": {
    "_class": "style",
    "blur": {
      "_class": "blur",
      "center": "{0.5, 0.5}",
      "do_objectID": "427D4715-FF7E-4424-9875-6988D1AD4E82",
      "isEnabled": false,
      "motionAngle": 0,
      "radius": 5,
      "saturation": 1,
      "type": 0
    },
    "do_objectID": "C99F77A7-5B2E-4BEB-B3A1-965B37F132DF",
    "endMarkerType": 0,
    "miterLimit": 10,
    "startMarkerType": 0,
    "textStyle": {
      "_class": "textStyle",
      "do_objectID": "832D0762-21D3-4718-90C4-686687783F62",
      "encodedAttributes": {
        "MSAttributedStringColorAttribute": {
          "_class": "color",
          "alpha": 1,
          "blue": 0.2392156863,
          "green": 0.1333333333,
          "red": 0.01176470588
        },
        "MSAttributedStringFontAttribute": {
          "_class": "fontDescriptor",
          "attributes": {
            "name": "HelveticaNeue",
            "size": 14
          }
        },
        "kerning": 0,
        "paragraphStyle": {
          "_class": "paragraphStyle",
          "alignment": 1,
          "allowsDefaultTighteningForTruncation": 0,
          "maximumLineHeight": 20,
          "minimumLineHeight": 20
        }
      },
      "verticalAlignment": 0
    },
    "windingRule": 1
  },
  "textBehaviour": 0
}