{
  "_class": "shapePath",
  "booleanOperation": -1,
  "clippingMaskMode": 0,
  "do_objectID": "4AFB46FD-937C-4147-AFE1-BA416E1B8D42",
  "edited": true,
  "exportOptions": {
    "_class": "exportOptions",
    "do_objectID": "009985B4-93D9-4BA5-BBB5-B36A073155DD",
    "exportFormats": [
    ],
    "includedLayerIds": [
    ],
    "layerOptions": 0,
    "shouldTrim": false
  },
  "frame": {
    "_class": "rect",
    "constrainProportions": false,
    "do_objectID": "25EABD94-9D8D-4C61-89E7-A6A266B2D416",
    "height": 2,
    "width": 359,
    "x": 16,
    "y": 689
  },
  "hasClippingMask": false,
  "isClosed": false,
  "isFixedToViewport": false,
  "isFlippedHorizontal": false,
  "isFlippedVertical": false,
  "isLocked": false,
  "isVisible": true,
  "layerListExpandedType": 0,
  "name": "Line 2 Copy 14",
  "nameIsFixed": false,
  "pointRadiusBehaviour": 1,
  "points": [
    {
      "_class": "curvePoint",
      "cornerRadius": 0,
      "curveFrom": "{0, 0.49999999999999972}",
      "curveMode": 1,
      "curveTo": "{0, 0.49999999999999972}",
      "hasCurveFrom": false,
      "hasCurveTo": false,
      "point": "{6.0715321659188248e-16, 0.49999999999999994}"
    },
    {
      "_class": "curvePoint",
      "cornerRadius": 0,
      "curveFrom": "{0, 0.49999999999999972}",
      "curveMode": 1,
      "curveTo": "{0, 0.49999999999999972}",
      "hasCurveFrom": false,
      "hasCurveTo": false,
      "point": "{0.99999999999999978, 0.50000000000000433}"
    }
  ],
  "resizingConstraint": 63,
  "resizingType": 0,
  "rotation": 0,
  "shouldBreakMaskChain": false,
  "style": {
    "_class": "style",
    "borderOptions": {
      "_class": "borderOptions",
      "dashPattern": [
      ],
      "do_objectID": "079C1ED9-DE56-46B7-A37C-023E3EF8D031",
      "isEnabled": false,
      "lineCapStyle": 2,
      "lineJoinStyle": 0
    },
    "borders": [
      {
        "_class": "border",
        "color": {
          "_class": "color",
          "alpha": 1,
          "blue": 0.9019607843137255,
          "green": 0.8784313725490196,
          "red": 0.8549019607843137
        },
        "fillType": 0,
        "isEnabled": true,
        "position": 0,
        "thickness": 1
      }
    ],
    "do_objectID": "4C69D854-EBC7-4046-BC10-ED394E33C13B",
    "endMarkerType": 0,
    "fills": [
      {
        "_class": "fill",
        "color": {
          "_class": "color",
          "alpha": 1,
          "blue": 0.847,
          "green": 0.847,
          "red": 0.847
        },
        "fillType": 0,
        "isEnabled": false,
        "noiseIndex": 0,
        "noiseIntensity": 0,
        "patternFillType": 1,
        "patternTileScale": 1
      }
    ],
    "miterLimit": 10,
    "startMarkerType": 0,
    "windingRule": 1
  }
}