{
  "_class": "shapeGroup",
  "booleanOperation": 0,
  "clippingMaskMode": 0,
  "do_objectID": "15479121-A8B4-439E-89EE-ABD0EE414495",
  "exportOptions": {
    "_class": "exportOptions",
    "do_objectID": "0D224333-C1DF-4CCC-B2E4-81ED8A0EE16E",
    "exportFormats": [
    ],
    "includedLayerIds": [
    ],
    "layerOptions": 0,
    "shouldTrim": false
  },
  "frame": {
    "_class": "rect",
    "constrainProportions": false,
    "do_objectID": "089C2CB2-198B-4930-85D7-03C2CBAD9310",
    "height": 9,
    "width": 12,
    "x": 71,
    "y": 2.999999999999943
  },
  "groupLayout": {
    "_class": "MSImmutableFreeformGroupLayout",
    "do_objectID": "F3A09E5E-FAEF-40AF-9EC2-8592D92CCE94"
  },
  "hasClickThrough": true,
  "hasClippingMask": false,
  "isFixedToViewport": false,
  "isFlippedHorizontal": false,
  "isFlippedVertical": false,
  "isLocked": false,
  "isVisible": true,
  "layerListExpandedType": 0,
  "layers": [
    {
      "class": "shapePath",
      "id": "CD11F040-7798-4040-826E-28254C5A8FDF"
    },
    {
      "class": "shapePath",
      "id": "9E3B15D5-2764-42C8-A02B-EE7F3E91A940"
    },
    {
      "class": "shapePath",
      "id": "92BDCF8D-7628-44FD-8D1B-8647B861D4F5"
    }
  ],
  "name": "Wifi",
  "nameIsFixed": true,
  "resizingConstraint": 63,
  "resizingType": 0,
  "rotation": 0,
  "shouldBreakMaskChain": false,
  "style": {
    "_class": "style",
    "blur": {
      "_class": "blur",
      "center": "{0.5, 0.5}",
      "do_objectID": "922EB933-1356-4CF2-95BE-36FEC789A86F",
      "isEnabled": false,
      "motionAngle": 0,
      "radius": 5,
      "saturation": 1,
      "type": 0
    },
    "borders": [
      {
        "_class": "border",
        "color": {
          "_class": "color",
          "alpha": 1,
          "blue": 0,
          "green": 0,
          "red": 0
        },
        "fillType": 0,
        "isEnabled": false,
        "position": 0,
        "thickness": 1
      }
    ],
    "do_objectID": "756CE606-78A7-46A1-9DD1-E338DD98047E",
    "endMarkerType": 0,
    "fills": [
      {
        "_class": "fill",
        "color": {
          "_class": "color",
          "alpha": 1,
          "blue": 0,
          "green": 0,
          "red": 0
        },
        "fillType": 0,
        "isEnabled": true,
        "noiseIndex": 0,
        "noiseIntensity": 0,
        "patternFillType": 0,
        "patternTileScale": 1
      }
    ],
    "miterLimit": 10,
    "startMarkerType": 0,
    "windingRule": 1
  },
  "windingRule": 1
}