{
  "_class": "artboard",
  "backgroundColor": {
    "_class": "color",
    "alpha": 1,
    "blue": 1,
    "do_objectID": "6BA3F452-962B-4B77-B5BC-57563D7894AA",
    "green": 1,
    "red": 1
  },
  "booleanOperation": -1,
  "clippingMaskMode": 0,
  "do_objectID": "1F52EDAA-E528-4D3E-A2DC-5CDA8C0D9E95",
  "exportOptions": {
    "_class": "exportOptions",
    "do_objectID": "E734562D-290B-4341-9B28-9E0BA4950E63",
    "exportFormats": [
      {
        "_class": "exportFormat",
        "absoluteSize": 0,
        "fileFormat": "png",
        "name": "",
        "namingScheme": 0,
        "scale": 2,
        "visibleScaleType": 0
      }
    ],
    "includedLayerIds": [
    ],
    "layerOptions": 0,
    "shouldTrim": false
  },
  "frame": {
    "_class": "rect",
    "constrainProportions": false,
    "do_objectID": "A3C1355E-B309-4B2C-896C-CC9E1321826A",
    "height": 667,
    "width": 375,
    "x": 1873,
    "y": -375
  },
  "grid": {
    "_class": "simpleGrid",
    "do_objectID": "EC00C744-FECC-454D-A3F0-16287BA12860",
    "gridSize": 8,
    "isEnabled": false,
    "thickGridTimes": 8
  },
  "groupLayout": {
    "_class": "MSImmutableFreeformGroupLayout",
    "do_objectID": "4A6340C4-C5E3-4767-B473-5F1407F10BEE"
  },
  "hasBackgroundColor": false,
  "hasClickThrough": false,
  "hasClippingMask": false,
  "horizontalRulerData": {
    "_class": "rulerData",
    "base": 0,
    "do_objectID": "9222D398-2E5D-4676-A9CC-7E1688055B08",
    "guides": [
    ]
  },
  "includeBackgroundColorInExport": true,
  "includeInCloudUpload": true,
  "isFixedToViewport": false,
  "isFlippedHorizontal": false,
  "isFlippedVertical": false,
  "isFlowHome": false,
  "isLocked": false,
  "isVisible": true,
  "layerListExpandedType": 2,
  "layers": [
    {
      "class": "symbolInstance",
      "id": "032CF184-3C0F-428A-B178-CB42AFEF20ED"
    },
    {
      "class": "rectangle",
      "id": "A728141B-2467-4A57-8CFC-97B90508EA2E"
    },
    {
      "class": "shapePath",
      "id": "A1C95640-0F3B-4EF8-9F5A-71C9305CD1CE"
    },
    {
      "class": "shapePath",
      "id": "DB2817B6-B0EE-4FF9-8DFF-81048841C39A"
    },
    {
      "class": "shapePath",
      "id": "0169B82D-5658-4E6C-B11B-C57E909D5AB0"
    },
    {
      "class": "rectangle",
      "id": "E9988258-D07F-42E4-8A68-B5124582CD94"
    },
    {
      "class": "oval",
      "id": "E10FAEC9-1D38-4852-9F06-857407B0C9B5"
    },
    {
      "class": "group",
      "id": "A81B8CDE-D133-472F-83D9-F79F05BFAA6B"
    },
    {
      "class": "shapePath",
      "id": "56C199D4-ABA5-4304-9621-6A4811C26260"
    },
    {
      "class": "group",
      "id": "7D7E66DF-BDA0-4750-BB3C-C1B4BFA54D6A"
    },
    {
      "class": "group",
      "id": "2454ADC3-9D89-43AC-B85A-3E43F13A9396"
    },
    {
      "class": "group",
      "id": "6097A3FF-7EDC-4A38-82A6-C84918AF4751"
    },
    {
      "class": "group",
      "id": "2686CE3D-93D1-4421-B552-6D3E1BE8F7CA"
    },
    {
      "class": "rectangle",
      "id": "2ABCBF57-CA95-460F-A0AF-E91BA51225D8"
    },
    {
      "class": "text",
      "id": "BC2EA4D3-0891-47AF-9542-DE2BBF9AE28E"
    },
    {
      "class": "oval",
      "id": "C9BC72F6-14B8-4364-8B2C-E0064D192463"
    },
    {
      "class": "symbolInstance",
      "id": "954CFFD8-4498-4EFC-9076-509638D7F6AC"
    },
    {
      "class": "symbolInstance",
      "id": "2D533D19-0042-4BBC-B28E-6A3441DDD788"
    },
    {
      "class": "symbolInstance",
      "id": "4B636000-B972-4C74-A2A2-87D0BB93D4C2"
    },
    {
      "class": "group",
      "id": "8F8EF891-6AED-45C7-BA89-D55AC2836145"
    },
    {
      "class": "symbolInstance",
      "id": "04560AF6-0DD2-4CFD-970F-D69531AB5263"
    },
    {
      "class": "group",
      "id": "3ACCE699-22B6-4CEF-BE60-9678589AE4F3"
    },
    {
      "class": "text",
      "id": "F5CFC08C-DDBF-4EC2-A3F3-74FEDF5AC8F0"
    }
  ],
  "layout": {
    "_class": "layoutGrid",
    "columnWidth": 60,
    "do_objectID": "2B291D31-F6F4-4853-8FDF-D88B1856B422",
    "drawHorizontal": true,
    "drawHorizontalLines": false,
    "drawVertical": false,
    "gutterHeight": 4,
    "gutterWidth": 20,
    "guttersOutside": true,
    "horizontalOffset": 0,
    "isEnabled": false,
    "numberOfColumns": 12,
    "rowHeightMultiplication": 1,
    "totalWidth": 960
  },
  "name": "beneficiaries-05",
  "nameIsFixed": true,
  "resizesContent": false,
  "resizingConstraint": 63,
  "resizingType": 0,
  "rotation": 0,
  "shouldBreakMaskChain": true,
  "style": {
    "_class": "style",
    "do_objectID": "C622EAB5-C942-4CB8-9FE2-506EFD45AD8F",
    "endMarkerType": 0,
    "miterLimit": 10,
    "startMarkerType": 0,
    "windingRule": 1
  },
  "verticalRulerData": {
    "_class": "rulerData",
    "base": 0,
    "do_objectID": "231280A7-D016-4B14-A69D-C9CD947BC721",
    "guides": [
    ]
  }
}