{
  "_class": "group",
  "booleanOperation": -1,
  "clippingMaskMode": 0,
  "do_objectID": "6094EBAE-2227-4062-A1B4-B4EA3F327497",
  "exportOptions": {
    "_class": "exportOptions",
    "do_objectID": "4F167277-FC81-4594-BDF8-41A6ECA02AF4",
    "exportFormats": [
    ],
    "includedLayerIds": [
    ],
    "layerOptions": 0,
    "shouldTrim": false
  },
  "frame": {
    "_class": "rect",
    "constrainProportions": false,
    "do_objectID": "09CB9BEC-FFBA-4EFA-AA28-161F8831F4BA",
    "height": 32,
    "width": 32,
    "x": -9.094947017729282e-13,
    "y": 0
  },
  "groupLayout": {
    "_class": "MSImmutableFreeformGroupLayout",
    "do_objectID": "15BC7E8C-92C1-4CFB-AAF5-CB89637608D6"
  },
  "hasClickThrough": false,
  "hasClippingMask": false,
  "isFixedToViewport": false,
  "isFlippedHorizontal": false,
  "isFlippedVertical": false,
  "isLocked": false,
  "isVisible": true,
  "layerListExpandedType": 0,
  "layers": [
    {
      "class": "oval",
      "id": "3C2F34B6-016E-4DE3-8B81-F0D12038E29A"
    },
    {
      "class": "group",
      "id": "78F11199-CA33-4442-9B03-74DDE23FAFD4"
    }
  ],
  "name": "Group 6",
  "nameIsFixed": false,
  "resizingConstraint": 63,
  "resizingType": 0,
  "rotation": 0,
  "shouldBreakMaskChain": false,
  "style": {
    "_class": "style",
    "do_objectID": "1767B651-9077-4C38-84A8-4F0F0CDE5E53",
    "endMarkerType": 0,
    "miterLimit": 10,
    "startMarkerType": 0,
    "windingRule": 1
  }
}