{
  "_class": "group",
  "booleanOperation": -1,
  "clippingMaskMode": 0,
  "do_objectID": "B5D6BC54-4580-483A-8042-3AED3C45530F",
  "exportOptions": {
    "_class": "exportOptions",
    "do_objectID": "9609C04B-1C62-419E-B331-5DB6A2A4006B",
    "exportFormats": [
    ],
    "includedLayerIds": [
    ],
    "layerOptions": 0,
    "shouldTrim": false
  },
  "frame": {
    "_class": "rect",
    "constrainProportions": false,
    "do_objectID": "3BEE6CB9-A70D-4BAB-A821-A1908C169EBA",
    "height": 14,
    "width": 360,
    "x": 0.5,
    "y": 0.8250142450142448
  },
  "groupLayout": {
    "_class": "MSImmutableFreeformGroupLayout",
    "do_objectID": "CC763CA1-C848-4E11-AAC3-AEAB45FCC511"
  },
  "hasClickThrough": false,
  "hasClippingMask": false,
  "isFixedToViewport": false,
  "isFlippedHorizontal": false,
  "isFlippedVertical": false,
  "isLocked": false,
  "isVisible": true,
  "layerListExpandedType": 0,
  "layers": [
    {
      "class": "group",
      "id": "0B8D294F-ECAE-4BB1-B1E7-DD207A1A0240"
    },
    {
      "class": "text",
      "id": "459B9FD4-AECA-49F5-89FF-888EB49EF941"
    },
    {
      "class": "group",
      "id": "37392598-CE2A-46F1-9F01-8FDF7FB76772"
    }
  ],
  "name": "Group 3",
  "nameIsFixed": false,
  "resizingConstraint": 63,
  "resizingType": 0,
  "rotation": 0,
  "shouldBreakMaskChain": false,
  "style": {
    "_class": "style",
    "do_objectID": "B53FB01C-C9D4-46A6-85B7-498E344FADB9",
    "endMarkerType": 0,
    "miterLimit": 10,
    "startMarkerType": 0,
    "windingRule": 1
  }
}