{
  "_class": "group",
  "booleanOperation": -1,
  "clippingMaskMode": 0,
  "do_objectID": "1A2A44AE-5147-4773-980C-8B79F50540B1",
  "exportOptions": {
    "_class": "exportOptions",
    "do_objectID": "C15EF51D-9B57-45E3-802D-9FAD7739443D",
    "exportFormats": [
    ],
    "includedLayerIds": [
    ],
    "layerOptions": 0,
    "shouldTrim": false
  },
  "frame": {
    "_class": "rect",
    "constrainProportions": false,
    "do_objectID": "5E2F6D51-98AB-4EFD-8E33-3CAD18E3907D",
    "height": 22,
    "width": 186,
    "x": 0,
    "y": 0
  },
  "groupLayout": {
    "_class": "MSImmutableFreeformGroupLayout",
    "do_objectID": "A753EABF-EECC-4CCC-8396-68B5A9A1989B"
  },
  "hasClickThrough": false,
  "hasClippingMask": false,
  "isFixedToViewport": false,
  "isFlippedHorizontal": false,
  "isFlippedVertical": false,
  "isLocked": false,
  "isVisible": true,
  "layerListExpandedType": 0,
  "layers": [
    {
      "class": "text",
      "id": "68B0B8E1-5E0D-471C-AEE5-D1B855B93A3C"
    },
    {
      "class": "shapeGroup",
      "id": "A6B6AF20-4DBC-47F5-AFFE-53923245EF05"
    }
  ],
  "name": "Group 5",
  "nameIsFixed": false,
  "resizingConstraint": 63,
  "resizingType": 0,
  "rotation": 0,
  "shouldBreakMaskChain": false,
  "style": {
    "_class": "style",
    "do_objectID": "4EA7581D-D8C2-4892-8147-B9799F56A6CE",
    "endMarkerType": 0,
    "miterLimit": 10,
    "startMarkerType": 0,
    "windingRule": 1
  }
}